README.md
setup.py
betanegbinfit/__init__.py
betanegbinfit/betacdnb.py
betanegbinfit/betainc.py
betanegbinfit/bridge_mixalime.py
betanegbinfit/cdnb.py
betanegbinfit/combine.py
betanegbinfit/create.py
betanegbinfit/distributions.py
betanegbinfit/hyp.py
betanegbinfit/plot.py
betanegbinfit/stats.py
betanegbinfit/tests.py
betanegbinfit/utils.py
betanegbinfit.egg-info/PKG-INFO
betanegbinfit.egg-info/SOURCES.txt
betanegbinfit.egg-info/dependency_links.txt
betanegbinfit.egg-info/requires.txt
betanegbinfit.egg-info/top_level.txt
betanegbinfit/models/__init__.py
betanegbinfit/models/model.py
betanegbinfit/models/model_line.py
betanegbinfit/models/model_line_lrt.py
betanegbinfit/models/model_mixture.py
betanegbinfit/models/model_mixtures.py
betanegbinfit/models/model_window.py